sadedegel/__init__.py
sadedegel/__main__.py
sadedegel/about.py
sadedegel/config.py
sadedegel/default.ini
sadedegel/tfidf.py
sadedegel/bblock/__init__.py
sadedegel/bblock/doc.py
sadedegel/bblock/sbd.py
sadedegel/bblock/token.py
sadedegel/bblock/util.py
sadedegel/bblock/vocabulary.py
sadedegel/bblock/word_tokenizer.py
sadedegel/bblock/word_tokenizer_helper.py
sadedegel/bblock/cli/__init__.py
sadedegel/bblock/cli/__main__.py
sadedegel/bblock/data/stop-words.txt
sadedegel/bblock/data/bert/vocabulary.hdf5
sadedegel/bblock/data/icu/vocabulary.hdf5
sadedegel/bblock/data/simple/vocabulary.hdf5
sadedegel/dataset/__init__.py
sadedegel/dataset/__main__.py
sadedegel/dataset/_core.py
sadedegel/dataset/util.py
sadedegel/dataset/annotated/300-330-40265684.json
sadedegel/dataset/annotated/7-mucize-bitki-40745659.json
sadedegel/dataset/annotated/al-i-imran-suresi-ve-dualar-29509828.json
sadedegel/dataset/annotated/amator-muyuz-profesyonel-miyiz-18592660.json
sadedegel/dataset/annotated/aydin-candabak-hakkaride-blucinli-kizlar-39167075.json
sadedegel/dataset/annotated/baris-harekati-ndan-beri-guney-in-basina-gelen-en-buyuk-felaket-18270944.json
sadedegel/dataset/annotated/basari-saglikli-zihinden-gecer-41355020.json
sadedegel/dataset/annotated/bayramda-kilo-almamak-icin-7-yol-41233020.json
sadedegel/dataset/annotated/bilmem-anlatabiliyor-muyum-85618.json
sadedegel/dataset/annotated/bir-gunluk-ask-22591626.json
sadedegel/dataset/annotated/bir-tek-galibiyet-golu-eksikti-41119625.json
sadedegel/dataset/annotated/bir-varmis-bir-yokmus-16145006.json
sadedegel/dataset/annotated/bitmemis-evlilikler-375881.json
sadedegel/dataset/annotated/bosuna-nefes-tuketme-11274929.json
sadedegel/dataset/annotated/bozcaada-ya-nasil-gidemedik-4716965.json
sadedegel/dataset/annotated/bu-minik-yavruyu-evlat-edinmek-ister-misiniz-34822251.json
sadedegel/dataset/annotated/bulgaristan-secimine-verilen-destegin-yansimalari-7712763.json
sadedegel/dataset/annotated/cinayet-adaleti-17735219.json
sadedegel-0.21.2.dist-info/LICENSE
sadedegel-0.21.2.dist-info/METADATA
sadedegel-0.21.2.dist-info/WHEEL
sadedegel-0.21.2.dist-info/entry_points.txt
sadedegel-0.21.2.dist-info/top_level.txt
sadedegel-0.21.2.dist-info/RECORD
