Metadata-Version: 2.1
Name: sadedegel
Version: 0.21.2
Summary: Extraction-based Turkish news summarizer.
Home-page: https://github.com/GlobalMaksimum/sadedegel
Author: Global Maksimum AI
Author-email: info@sadedegel.ai
License: MIT
Platform: UNKNOWN
Classifier: Development Status :: 3 - Alpha
Classifier: Environment :: Console
Classifier: Intended Audience :: Developers
Classifier: Intended Audience :: Science/Research
Classifier: License :: OSI Approved :: MIT License
Classifier: Operating System :: POSIX :: Linux
Classifier: Operating System :: MacOS :: MacOS X
Classifier: Operating System :: Microsoft :: Windows
Classifier: Programming Language :: Python :: 3.6
Classifier: Programming Language :: Python :: 3.7
Classifier: Programming Language :: Python :: 3.8
Classifier: Programming Language :: Python :: 3.9
Classifier: Topic :: Scientific/Engineering
Requires-Python: >=3.6
License-File: LICENSE
Requires-Dist: loguru (>=0.5.1)
Requires-Dist: click (>=7.1.2)
Requires-Dist: smart-open (==2.0.0)
Requires-Dist: uvicorn (>=0.11.8)
Requires-Dist: fastapi (>=0.61.0)
Requires-Dist: scikit-learn (==0.23.1)
Requires-Dist: nltk (>=3.6.6)
Requires-Dist: networkx (==2.4)
Requires-Dist: tabulate (>=0.8.7)
Requires-Dist: sadedegel-icu
Requires-Dist: requests
Requires-Dist: rich
Requires-Dist: cached-property
Requires-Dist: h5py (<=3.2.1,>=3.1.0)
Provides-Extra: bert
Requires-Dist: sentence-transformers ; extra == 'bert'
Provides-Extra: w2v
Requires-Dist: gensim ; extra == 'w2v'
